cpuprofile/__init__.py
cpuprofile/cpuprofile.py
cpuprofile-1.0.1.dist-info/METADATA
cpuprofile-1.0.1.dist-info/RECORD
cpuprofile-1.0.1.dist-info/WHEEL
cpuprofile-1.0.1.dist-info/top_level.txt
