Metadata-Version: 2.1
Name: cpuprofile
Version: 1.0.1
Summary: A simple Python package to profile CPU speed by computing the Fibonacci sequence
Home-page: https://github.com/muckrock/cpuprofile
Author: Dylan Freedman
Author-email: freedmand@gmail.com
License: UNKNOWN
Platform: UNKNOWN
Classifier: Programming Language :: Python :: 3
Classifier: License :: OSI Approved :: MIT License
Classifier: Operating System :: OS Independent
